pygame_builder/__init__.py
pygame_builder/element.py
pygame_builder/image.py
pygame_builder/main.py
pygame_builder/music.py
pygame_builder/sound.py
pygame_builder-0.2.1.dist-info/LICENSE
pygame_builder-0.2.1.dist-info/METADATA
pygame_builder-0.2.1.dist-info/WHEEL
pygame_builder-0.2.1.dist-info/top_level.txt
pygame_builder-0.2.1.dist-info/RECORD
