Metadata-Version: 2.1
Name: pygame_builder
Version: 0.2.1
Summary: A package to build games with ease.
Home-page: https://github.com/dehadeaaryan/pygame-builder
Author: Aaryan Dehade
Author-email: aaryandehade@adehade.tech
License: UNKNOWN
Project-URL: Bug Tracker, https://github.com/dehadeaaryan/pygame-builder/issues
Platform: UNKNOWN
Classifier: Programming Language :: Python :: 3
Classifier: License :: OSI Approved :: MIT License
Classifier: Operating System :: OS Independent
Requires-Python: >=3.6
License-File: LICENSE
